Workbook

Sheet LEVANTAMENTO DE CAMPO
A1: AUDITORIA DE SEGURANÇA RESIDENCIAL 2026 - LEVANTAMENTO DE CAMPO
A2: Código | B2: Categoria | C2: Pergunta | D2: Resposta | E2: Peso | F2: Observações
A3: P01 | B3: PERÍMETRO | C3: Tipo de imóvel | E3: 15
A4: P02 | B4: PERÍMETRO | C4: Metragem do terreno/área externa | E4: 5
A5: P03 | B5: PERÍMETRO | C5: Tipo de muro/cerca | E5: 15
A6: P04 | B6: PERÍMETRO | C6: Quantidade de portas externas | E6: 8
A7: P05 | B7: PERÍMETRO | C7: Quantidade de janelas acessíveis do solo (<2,5m) | E7: 10
A8: P06 | B8: PERÍMETRO | C8: Tipo de garagem/estacionamento | E8: 5
A9: P07 | B9: PERÍMETRO | C9: Gradil/proteção em janelas | E9: 10
A10: I01 | B10: ILUMINAÇÃO | C10: Iluminação externa noturna principal | E10: 8
A11: I02 | B11: ILUMINAÇÃO | C11: Pontos de iluminação no perímetro | E11: 5
A12: I03 | B12: ILUMINAÇÃO | C12: Iluminação de emergência (falta de energia) | E12: 3
A13: I04 | B13: ILUMINAÇÃO | C13: Visibilidade da rua para o interior | E13: 5
A14: A01 | B14: ACESSO | C14: Tipo de fechadura porta principal | E14: 10
... A34: H08 | B34: HUMANO | C34: Índice de criminalidade do bairro/região | E34: 10
A36: 💡 INSTRUÇÕES: Todas as perguntas possuem menu suspenso (clique na célula). Se nenhuma opção se aplicar, selecione "Outro (especificar)" e detalhe na coluna Observações (F).

Sheet LISTAS_OPCOES
A1: P01 | B1: P02 | C1: P03 | D1: P04 | E1: P05 | F1: P06 | G1: P07 | H1: I01 | I1: I02 | J1: I03 | K1: I04 | L1: A01 | M1: A02 | N1: A03 | O1: A04 | P1: A05 | Q1: E01 | R1: E02 | S1: E03 | T1: E04 | U1: E05 | V1: E06 | W1: E07 | X1: E08 | Y1: H01 | Z1: H02 | AA1: H03 | AB1: H04 | AC1: H05 | AD1: H06 | AE1: H07 | AF1: H08
A2: Casa térrea | B2: 0-50m² (sem área) | C2: Nenhum | D2: 0 (apenas portão) | E2: 0 janelas | F2: Não possui | G2: Nenhuma proteção | H2: Nenhuma | I2: 0 pontos | J2: Não possui | K2: Visibilidade total | L2: Comum padrão | M2: Madeira oca | N2: Nenhuma | O2: Não existe | P2: Não possui | Q2: Não possui | R2: Nenhum | S2: Nenhum | T2: Nenhuma | U2: N/A | V2: N/A | W2: Não possui | X2: Nenhuma | Y2: Sempre vazia | Z2: Nunca viaja | AA2: Não possui | AB2: Inexistente | AC2: Nenhuma interação | AD2: Perfis públicos localização sempre | AE2: Nenhum | AF2: Muito baixo <5/1000
A3: Sobrado 2 andares | B3: 51-100m² | C3: Cerca viva/plantas | D3: 1 porta | E3: 1 janela | F3: Vaga rua descoberta | G3: Apenas telas | H3: Manual liga/desliga | I3: 1 ponto (entrada) | J3: Lanternas manuais | K3: Alta (70-90%) | L3: Comum dupla | M3: Madeira semi-maciça | N3: Ferrolho simples 1pt | O3: Madeira básica | P3: Interfone áudio simples | Q3: Simulador adesivos | R3: 1 sensor (porta) | S3: 1 sensor (sala) | T3: 1 câmera (entrada) | U3: Analógica baixa | V3: Sem gravação | W3: Fixo 1 ponto | X3: Lâmpadas smart | Y3: Vazia 80-90% | Z3: Raramente 1x/ano | AA3: Gato | AB3: Policiamento 1x/semana | AC3: Apenas cumprimento | AD3: Posta tempo real | AE3: Tentativa furto carro | AF3: Baixo 5-15/1000
A4: Sobrado 3+ andares | B4: 101-200m² | C4: Alambrado <1,2m | D4: 2 portas | E4: 2 janelas | F4: Vaga rua coberta | G4: <25% protegidas | H4: Timer fixo | I4: 2 pontos (frente) | J4: Luminárias 1-2 pontos | K4: Média (40-70%) | L4: Tetra 40mm | M4: Madeira maciça básica | N4: Ferrolho reforçado | O4: Madeira reforçada | P4: Interfone múltiplos pontos | Q4: Simulador adesivos+sirene | R4: 2 sensores | S4: 2 sensores (sala+corredor) | T4: 2 câmeras (frente) | U4: Analógica SD 480p | V4: DVR 3 dias | W4: Fixos 2-3 pontos | X4: Tomadas smart | Y4: Vazia 50-70% | Z4: 2-3x/ano | AA4: Cão <10kg | AB4: Policiamento 2-3x/semana | AC4: Conhece casualmente | AD4: Marca locais ocasional | AE4: Tentativa arrombamento | AF4: Médio-baixo 15-30/1000
A5: Apartamento térreo | B5: 201-300m² | C5: Alambrado 1,2-1,8m | D5: 3 portas | E5: 3 janelas | F5: Garagem sem portão | G5: 25-50% protegidas | H5: Timer programável | I5: 3 pontos | J5: Sistema 3-5 pontos | K5: Baixa (10-40%) | L5: Tetra 60mm | M5: Madeira maciça nobre | N5: Catenária básica | O5: Metal básico | P5: Vídeo P&B | Q5: Central local básica | R5: 3 sensores | S5: 3-4 sensores | T5: 3 câmeras | U5: HD 720p | V5: DVR 7 dias | W5: Fixos 4+ pontos | X5: Smart speakers | Y5: Presença 20-40% | Z5: 4-8x/ano | AA5: Cão 10-15kg | AB5: Viatura diária | AC5: Bom relacionamento | AD5: Posta após retornar | AE5: Furto objetos externos | AF5: Médio 30-50/1000
A6: Apartamento 1º andar | B6: 301-500m² | C6: Alambrado >1,8m | D6: 4 portas | E6: 4-6 janelas | F6: Portão manual simples | G6: 50-75% protegidas | H6: Fotocélula | I6: 4-6 pontos | J6: Sistema >5 pontos | K6: Muito baixa (<10%) | L6: Tetra cilindro europeu | M6: MDF reforçado | N6: Catenária reforçada | O6: Metal reforçado | P6: Vídeo colorido | Q6: Central local 1-3 sensores | R6: 4-6 sensores | S6: 5-8 sensores | T6: 4 câmeras | U6: Full HD 1080p | V6: DVR 15 dias | W6: Controle portátil 1un | X6: Lâmpadas+tomadas | Y6: Presença 60-80% | Z6: 9-12x/ano | AA6: Cão 15-25kg | AB6: Ronda Municipal | AC6: Grupo WhatsApp informal | AD6: Nunca marca localização | AE6: Furto bicicleta/moto | AF6: Médio-alto 50-75/1000
A7: Apartamento 2º andar | B7: 501-1000m² | C7: Muro blocos <1,5m | D7: 5 portas | E7: 7-10 janelas | F7: Portão manual com tranca | G7: 75-90% protegidas | H7: Sensor PIR | I7: 7-10 pontos | J7: Bateria backup | K7: Bloqueada total | L7: Deadbolt simples | M7: Metal chapa fina | N7: Tranca Gorges | O7: Fechadura simples | P7: Vídeo digital 4" | Q7: Central local 4-8 sensores | R7: 7-10 sensores | S7: 9-12 sensores | T7: 5-7 câmeras | U7: 2K 1440p | V7: DVR 30 dias | W7: Controles 2-4un | X7: Integração 2 sistemas | Y7: Sempre alguém >90% | Z7: Mensalmente | AA7: Cão 25-35kg | AB7: Ronda privada 1x/dia | AC7: Grupo vigilância ativo | AD7: Nunca compartilha rotina | AE7: Furto arrombamento | AF7: Alto 75-100/1000
A8: Apartamento 3º-5º andar | B8: 1001-2000m² | C8: Muro blocos 1,5-2m | D8: 6-8 portas | E8: 11-15 janelas | F8: Portão basculante | G8: 100% protegidas | H8: Sensor microondas | I8: 11-15 pontos | J8: Gerador manual | K8: Película fumê | L8: Deadbolt reforçada | M8: Metal chapa grossa | N8: Múltiplos 2-3 | O8: Fechadura reforçada | P8: Vídeo digital 7"+ | Q8: Central local 9+ sensores | R8: 11-15 sensores | S8: >12 sensores | T8: 8-12 câmeras | U8: 4K 2160p | V8: NVR 60+ dias | W8: Controles 5+un | X8: Integração 3 sistemas | Y8: Home office 1 pessoa | Z8: Quinzenalmente | AA8: Cão 35-50kg | AB8: Ronda privada 2-3x/dia | AC8: Rede organizada | AD8: Perfil semi-privado | AE8: Roubo intimidação | AF8: Muito alto >100/1000
A9: Apartamento >5º andar | B9: 2001-5000m² | C9: Muro blocos 2-2,5m | D9: 9-12 portas | E9: 16-20 janelas | F9: Portão automático básico | G9: Grades fixas simples | H9: Sensor duplo PIR+MW | I9: >15 pontos | J9: Gerador automático | K9: Cortinas blackout | L9: Multiponto 3pts | M9: Aço reforçado | N9: Múltiplos 4+ | O9: Com tranca adicional | P9: IP gravação local | Q9: Monitorado 24h básico | R9: 16-20 sensores | S9: Áreas principais | T9: 13-20 câmeras | U9: 8K+ | V9: Cloud 7 dias | W9: Vestível pulseira | X9: Alarme+câmeras | Y9: Home office múltiplos | Z9: Semanalmente | AA9: Cão >50kg | AB9: Ronda privada 4-8x/dia | AC9: App comunitário | AD9: Perfil privado total | AE9: Invasão domiciliar | AF9: Crítico zona risco
A10: Cobertura | B10: 5001-10000m² | C10: Muro blocos >2,5m | D10: >12 portas | E10: 21-30 janelas | F10: Portão auto com sensor | G10: Grades reforçadas | H10: Faixa LED | I10: Cobertura 360° | J10: Nobreak luzes | K10: Persianas sempre baixas | L10: Multiponto 5pts | M10: Blindada nível I | N10: Trava de piso | O10: Bloqueada permanente | P10: IP gravação nuvem | Q10: Monitorado 24h completo | R10: >20 sensores | S10: Cobertura total | T10: >20 câmeras | U10: Visão noturna 5-10m | V10: Cloud 15 dias | W10: App smartphone básico | X10: Alarme+câmeras+iluminação | Y10: Idosos tempo integral | Z10: Viagens trabalho | AA10: Raça guarda | AB10: Ronda contínua 24h | AC10: Câmeras compartilhadas | AD10: Sem redes sociais | AE10: Sequestro relâmpago | AF10: Bairro nobre
A11: Chácara/Sítio <1000m² | B11: >10000m² | C11: Muro com grades topo | D11: Outro (especificar) | E11: >30 janelas | F11: Portão auto com controle | G11: Grades removíveis | H11: Refletores | I11: Apenas frente | J11: Solar independente | K11: Vegetação densa | L11: Multiponto 7+pts | M11: Blindada nível II | N11: Trava tetra auxiliar | O11: Bloqueada com alarme | P11: Smart com app | Q11: Monitorado vídeo verificação | R11: Todos acessos 100% | S11: PIR básico | T11: Cobertura frente | U11: Visão noturna 20-30m | V11: Cloud 30 dias | W11: App com GPS | X11: Alarme+câmeras+fechaduras | Y11: Crianças após escola | Z11: Ausências >1 semana | AA11: Raça guarda treinamento básico | AB11: Guarita entrada | AC11: Reuniões periódicas | AD11: Fotos sem geo | AE11: Múltiplas tentativas 2-3 | AF11: Bairro periférico
A12: Chácara/Sítio 1000-5000m² | B12: N/A (apartamento) | C12: Muro com espículas | E12: Todas >2,5m | F12: Portão auto biometria | G12: Grades decorativas | H12: Postes com lâmpadas | I12: Frente + fundos | J12: Outro (especificar) | K12: Muros + vegetação | L12: Eletrônica senha 4dig | M12: Blindada nível III | N12: Tranca eletrônica | O12: Gradeada + porta | P12: Smart reconhecimento facial | Q12: Smart DIY | R12: Apenas portas | S12: PIR pet 15kg | T12: Frente+fundos | U12: Visão noturna 40m+ | V12: Cloud 90+ dias | W12: Integrado central | X12: Central unificada | Y12: Empregada integral | Z12: Ausências >1 mês | AA12: Raça guarda profissional | AB12: Guarita+ronda | AC12: Contratação coletiva | AD12: Atraso 24h+ | AE12: Múltiplos 4+ | AF12: Dados indisponíveis
A13: Fazenda >5000m² | B13: Outro (especificar) | C13: Muro com cacos vidro | E13: Outro (especificar) | F13: Portão auto com app | G13: Grades com abertura | H13: Solar externa | I13: Perímetro completo | K13: Outro (especificar) | L13: Eletrônica senha 6+dig | M13: Blindada nível IV+ | N13: Barra transversal | O13: Outro (especificar) | P13: Integrado fechadura | Q13: Smart com app | R13: Apenas janelas | S13: PIR pet 25kg | T13: Perímetro completo | U13: Colorida noturna | V13: Híbrido local+nuvem | W13: Por voz Alexa/Google | X13: Com cenas automação | Y13: Turnos alternados | Z13: Casa temporada | AA13: Múltiplos 2-3 | AB13: Segurança 8h | AC13: Observam viagens | AD13: Consciência digital | AE13: Incidentes vizinhos | AF13: Consultado SSP
A14: Condomínio fechado | C14: Cerca elétrica ativa | F14: Garagem subterrânea | G14: Película 3M | H14: Smart WiFi | I14: Outro (especificar) | L14: Biométrica digital | M14: PVC reforçado | N14: Outro (especificar) | P14: Sistema completo abertura remota | Q14: Smart com IA | R14: Portas+janelas principais | S14: Microondas | T14: Perímetro+interior | U14: WDR | V14: Por movimento | W14: Botão oculto | X14: Com geofencing | Y14: Monitoramento remoto | Z14: Outro (especificar) | AA14: Múltiplos 4+ | AB14: Segurança 12h | AC14: Troca chaves | AD14: Outro (especificar) | AE14: Área histórico criminal | AF14: Outro (especificar)
A15: Flat/Apart-hotel | C15: Cerca elétrica + alarme | F15: Box fechado | G15: Vidro laminado | H15: Smart com app | L15: Biométrica facial | M15: Vidro temperado | P15: Outro (especificar) | Q15: Híbrido local+monitorado | R15: Portas+janelas+basculantes | S15: Duplo PIR+MW | T15: IA detecção pessoas | U15: HDR | V15: Contínua 24/7 | W15: Outro (especificar) | X15: Com IA/aprendizado | Y15: Outro (especificar) | AA15: Alarme som cachorro | AB15: Segurança 24h | AC15: Outro (especificar) | AE15: Outro (especificar)
A16: Loft | C16: Concertina dupla | F16: 2 portões (duplo) | G16: Vidro temperado | H16: Integrada alarme | L16: Smart Bluetooth | M16: Vidro laminado+metal | Q16: Múltiplas centrais | R16: Com fio | S16: Sensor cortina | T16: Reconhecimento facial | U16: Outro (especificar) | V16: Com redundância | X16: Controle voz completo | AA16: Outro (especificar) | AB16: Segurança armada
A17: Kitnet/Studio | C17: Muro + cerca + alarme | F17: Outro (especificar) | G17: Película + grades | H17: Colorida RGB | L17: Smart WiFi | M17: Alumínio reforçado | Q17: Com cerca elétrica | R17: Sem fio wireless | S17: Câmera detecção | T17: Leitura placas | V17: Outro (especificar) | X17: Outro (especificar) | AB17: Condomínio vigilância
A18: Geminado | C18: Outro (especificar) | G18: Persianas metálicas | H18: Holofotes | L18: Smart app+backup | M18: Porta cofre | Q18: Com botão pânico | R18: Outro (especificar) | S18: Outro (especificar) | T18: Câmeras PTZ | AB18: Câmeras comunitárias
A19: Outro (especificar) | G19: Outro (especificar) | H19: Outro (especificar) | L19: Yale Doorman | M19: Outro (especificar) | Q19: Outro (especificar) | T19: Outro (especificar) | AB19: Outro (especificar)
L20: Magnética
L21: Combo eletrônica+mecânica
L22: Outro (especificar)

Sheet MATRIZ DE RISCO
A1: CÁLCULO DE RISCO - PONTUAÇÃO AUTOMATIZADA
A3: CATEGORIA | B3: PONTOS PERDA | C3: PONTOS GANHO | D3: SUBTOTAL | E3: STATUS
A4: Perímetro e Estrutura | B4: =COUNTBLANK('LEVANTAMENTO DE CAMPO'!D3:D9)*12 -> 84 | C4: 0 | D4: =B4-C4 -> 84 | E4: =IF(D4>50,"🔴 CRÍTICO",IF(D4>25,"🟡 ATENÇÃO","🟢 OK")) -> 🔴 CRÍTICO
A5: Iluminação e Visibilidade | B5: =COUNTBLANK('LEVANTAMENTO DE CAMPO'!D10:D13)*9 -> 36 | C5: 0 | D5: =B5-C5 -> 36 | E5: =IF(D5>50,"🔴 CRÍTICO",IF(D5>25,"🟡 ATENÇÃO","🟢 OK")) -> 🟡 ATENÇÃO
A6: Controle de Acesso | B6: =COUNTBLANK('LEVANTAMENTO DE CAMPO'!D14:D18)*10 -> 50 | C6: 0 | D6: =B6-C6 -> 50 | E6: =IF(D6>50,"🔴 CRÍTICO",IF(D6>25,"🟡 ATENÇÃO","🟢 OK")) -> 🟡 ATENÇÃO
A7: Sistemas Eletrônicos | B7: =COUNTBLANK('LEVANTAMENTO DE CAMPO'!D19:D26)*13 -> 104 | C7: 0 | D7: =B7-C7 -> 104 | E7: =IF(D7>50,"🔴 CRÍTICO",IF(D7>25,"🟡 ATENÇÃO","🟢 OK")) -> 🔴 CRÍTICO
A8: Fatores Humanos | B8: =COUNTBLANK('LEVANTAMENTO DE CAMPO'!D27:D34)*13 -> 104 | C8: 0 | D8: =B8-C8 -> 104 | E8: =IF(D8>50,"🔴 CRÍTICO",IF(D8>25,"🟡 ATENÇÃO","🟢 OK")) -> 🔴 CRÍTICO
A10: PONTUAÇÃO TOTAL (0-100) | B10: =100-SUM(D4:D8) -> -278
A12: CLASSIFICAÇÃO | B12: =IF(B10<=35,"🔓 VULNERABILIDADE EXTREMA",IF(B10<=60,"🔐 PROTEÇÃO INSUFICIENTE",IF(B10<=80,"🔒 SEGURANÇA BÁSICA","🛡️ PADRÃO FORTIFICADO"))) -> 🔓 VULNERABILIDADE EXTREMA
A14: INDICADOR VISUAL | B14: =IF(B10<=35,"CRÍTICO",IF(B10<=60,"ALTO RISCO",IF(B10<=80,"MODERADO","PROTEGIDO"))) -> CRÍTICO

Sheet PLANO DE AÇÃO
A1: RECOMENDAÇÕES PRIORITÁRIAS DE SEGURANÇA
A2: Prior. | B2: Categoria | C2: Vulnerabilidade | D2: Solução | E2: Produto | F2: Investimento | G2: Instalação | H2: Impacto | I2: Link
A3: 1 | B3: ACESSO | C3: Fechadura inadequada | D3: Substituir por deadbolt tetra | E3: Papaiz 510 / Yale 500 | F3: R$ 180-250 | G3: DIY 30min | H3: +25% | I3: mercadolivre
A4: 1 | B4: ELETRÔNICA | C4: Sem sistema de alarme | D4: Instalar central monitorada | E4: Verisure Starter | F4: R$ 89/mês | G4: Profissional | H4: +40% | I4: verisure.com.br
A5: 2 | B5: ILUMINAÇÃO | C5: Iluminação insuficiente | D5: Sensor PIR 180° externo | E5: Intelbras ESP 360 A | F5: R$ 65 | G5: DIY 15min | H5: +15% | I5: mercadolivre
A6: 2 | B6: ELETRÔNICA | C6: Sem câmeras CFTV | D6: Kit 2 câmeras WiFi Full HD | E6: Tapo C200 / Intelbras | F6: R$ 320 | G6: DIY 1h | H6: +20% | I6: mercadolivre
A7: 2 | B7: PERÍMETRO | C7: Janelas sem proteção | D7: Instalar grades tubulares | E7: Serralheria local 25mm | F7: R$ 300/un | G7: Profissional | H7: +18% | I7: serralheiro
A8: 3 | B8: PERÍMETRO | C8: Muro baixo (<1,8m) | D8: Elevar para 2,2m + espículas | E8: Projeto customizado | F8: R$ 8.000+ | G8: 5 dias | H8: +35% | I8: pedreiro
A9: 3 | B9: AUTOMAÇÃO | C9: Ausências prolongadas | D9: Timer smart para luzes | E9: Positivo Casa Inteligente | F9: R$ 45 | G9: DIY 5min | H9: +8% | I9: mercadolivre
A12: RESUMO DE INVESTIMENTO
A13: Prioridade 1 (Crítico - implementar em 7 dias) | B13: R$ 500-1.000
A14: Prioridade 2 (Importante - implementar em 30 dias) | B14: R$ 800-1.500
A15: Prioridade 3 (Melhorias - implementar em 90 dias) | B15: R$ 8.000+
A16: INVESTIMENTO TOTAL ESTIMADO | B16: R$ 9.300-10.500

Sheet RELATÓRIO EXECUTIVO
A1: 🏠 CASA BLINDADA - AUDITORIA DE SEGURANÇA RESIDENCIAL 2026
A2: Data de Emissão: 01/02/2026 | D2: Código Auditoria: AUD-2026- | E2: =RANDBETWEEN(1000,9999) -> 9335
A3: ⚠️ CONFIDENCIAL - USO PESSOAL
A5: 1. RESUMO EXECUTIVO
A7: PONTUAÇÃO DE SEGURANÇA: | B7: ='MATRIZ DE RISCO'!B10 -> -278 | C7: / 100
A8: CLASSIFICAÇÃO: | B8: ='MATRIZ DE RISCO'!B12 -> 🔓 VULNERABILIDADE EXTREMA
A10: 2. ANÁLISE POR CATEGORIA
A11: Categoria | B11: Status | C11: Pontuação | D11: Observações
A12: Perímetro e Estrutura | B12: ⚠️ | C12: 45/100 | D12: Muro baixo, janelas desprotegidas
A13: Iluminação | B13: ❌ | C13: 30/100 | D13: Iluminação insuficiente
A14: Controle de Acesso | B14: ⚠️ | C14: 55/100 | D14: Fechaduras básicas
A15: Sistemas Eletrônicos | B15: ❌ | C15: 25/100 | D15: Sem alarme e câmeras
A16: Fatores Humanos | B16: 🟢 | C16: 70/100 | D16: Presença e vizinhança ativa
A18: 3. TOP 5 VULNERABILIDADES CRÍTICAS
A19: 1. Ausência de sistema de alarme monitorado (-15 pontos)
A20: 2. Fechaduras comuns na porta principal (-10 pontos)
A21: 3. Muro baixo ou inexistente (-15 pontos)
A22: 4. Janelas acessíveis sem grades (-10 pontos)
A23: 5. Iluminação externa inadequada (-8 pontos)
A25: 4. CRONOGRAMA DE IMPLEMENTAÇÃO
A26: Semana 1 (Dias 1-7): Fechaduras + sensores porta/janela
A27: Semana 2 (Dias 8-14): Iluminação externa + câmera entrada
A28: Semana 3 (Dias 15-21): Alarme monitorado (agendamento técnico)
A29: Semana 4 (Dias 22-30): Reforços estruturais + testes
A31: 5. ORÇAMENTO TOTAL
A32: Investimento Imediato (Prioridade 1): | B32: R$ 500-1.000
A33: Melhorias Graduais (Prioridade 2-3): | B33: R$ 8.800-9.500
A34: CUSTO TOTAL: | B34: R$ 9.300-10.500
A40: Documento gerado automaticamente | Casa Blindada Auditoria v3.0 | Validade: 6 meses
A41: Consultoria técnica: contato@casablindada.com.br | Para dúvidas, acesse nosso suporte
